AUTHORS.rst
CONTRIBUTING.rst
HISTORY.rst
LICENSE
MANIFEST.in
README.rst
setup.cfg
setup.py
cheaterutil/__init__.py
cheaterutil/cbutil.py
cheaterutil/cli.py
cheaterutil.egg-info/PKG-INFO
cheaterutil.egg-info/SOURCES.txt
cheaterutil.egg-info/dependency_links.txt
cheaterutil.egg-info/entry_points.txt
cheaterutil.egg-info/not-zip-safe
cheaterutil.egg-info/requires.txt
cheaterutil.egg-info/top_level.txt
docs/Makefile
docs/authors.rst
docs/conf.py
docs/contributing.rst
docs/history.rst
docs/index.rst
docs/installation.rst
docs/make.bat
docs/readme.rst
docs/usage.rst
tests/__init__.py
tests/test_cheaterutil.py