Metadata-Version: 2.1
Name: cheaterutil
Version: 0.0.1
Summary: A util used for discord bot developers
Home-page: https://github.com/CheatBetter/cheaterutil
Author: CheatBetter
Author-email: vitalistrashlool@gmail.com
License: MIT license
Keywords: cheaterutil
Platform: UNKNOWN
Classifier: Development Status :: 2 - Pre-Alpha
Classifier: Intended Audience :: Developers
Classifier: License :: OSI Approved :: MIT License
Classifier: Natural Language :: English
Classifier: Programming Language :: Python :: 3
Classifier: Programming Language :: Python :: 3.6
Classifier: Programming Language :: Python :: 3.7
Classifier: Programming Language :: Python :: 3.8
Requires-Python: >=3.6
License-File: LICENSE
License-File: AUTHORS.rst
